datachain_sources/__init__.py
datachain_sources/_utils.py
datachain_sources/bytes/__init__.py
datachain_sources/bytes/_pandas.py
datachain_sources/file.py
datachain_sources/files/__init__.py
datachain_sources/files/_file.py
datachain_sources/files/_ftp.py
datachain_sources/files/_http.py
datachain_sources/files/_jsonfile.py
datachain_sources/files/_local.py
datachain_sources/files/_pandas.py
datachain_sources/files/_sftp.py
datachain_sources/ftp.py
datachain_sources/http.py
datachain_sources/query/__init__.py
datachain_sources/query/_pandas.py
datachain_sources/sftp.py
datachain_sources/sharepoint.py
datachain_sources/sql.py
datachain_sources-0.1.3.dist-info/WHEEL
datachain_sources-0.1.3.dist-info/METADATA
datachain_sources-0.1.3.dist-info/RECORD
