Metadata-Version: 2.1
Name: datachain-sources
Version: 0.1.3
Summary: Sources for DataChain library.
License: GPL-3.0-or-later
Author: Rayane AMROUCHE
Author-email: rayaneamrouche@gmail.com
Requires-Python: >=3.8
Classifier: License :: OSI Approved :: GNU General Public License v3 or later (GPLv3+)
Classifier: Programming Language :: Python :: 3
Classifier: Programming Language :: Python :: 3.8
Classifier: Programming Language :: Python :: 3.9
Classifier: Programming Language :: Python :: 3.10
Classifier: Programming Language :: Python :: 3.11
Provides-Extra: http
Provides-Extra: kaggle
Provides-Extra: mysql
Provides-Extra: pgsql
Provides-Extra: salesforce
Provides-Extra: sftp
Provides-Extra: sharepoint
Provides-Extra: snowflake
Requires-Dist: azure-common (>=1.1.28,<2.0.0); extra == "sharepoint"
Requires-Dist: azure-storage-blob (>=12.14.1,<13.0.0); extra == "sharepoint"
Requires-Dist: azure-storage-common (>=2.1.0,<3.0.0); extra == "sharepoint"
Requires-Dist: cryptography (==38.0.4); extra == "snowflake"
Requires-Dist: datachain (>=1.0.0,<2.0.0)
Requires-Dist: mysqlclient (>=2.1.1,<3.0.0); extra == "mysql"
Requires-Dist: pandas (>=2.0.2,<3.0.0)
Requires-Dist: paramiko (>=3.2.0,<4.0.0); extra == "sftp"
Requires-Dist: psycopg2-binary (>=2.9.5,<3.0.0); extra == "pgsql"
Requires-Dist: python-dotenv (>=1.0.0,<2.0.0)
Requires-Dist: requests (>=2.31.0,<3.0.0); extra == "http"
Requires-Dist: shareplum (>=0.5.1,<0.6.0); extra == "sharepoint"
Requires-Dist: simple-salesforce (>=1.12.2,<2.0.0); extra == "salesforce"
Requires-Dist: snowflake-connector-python (>=2.9.0,<3.0.0); extra == "snowflake"
Requires-Dist: snowflake-sqlalchemy (>=1.4.4,<2.0.0); extra == "snowflake"
Requires-Dist: sqlalchemy (==1.4.46); extra == "snowflake" or extra == "mysql" or extra == "pgsql"
